LICENSE
MANIFEST.in
Makefile
README.rst
requirements-dev.txt
requirements.txt
setup.cfg
setup.py
btdht/__init__.py
btdht/dht.c
btdht/dht.pyx
btdht/exceptions.py
btdht/krcp.c
btdht/krcp.pxd
btdht/krcp.pyx
btdht/utils.c
btdht/utils.pyx
kkbtdht.egg-info/PKG-INFO
kkbtdht.egg-info/SOURCES.txt
kkbtdht.egg-info/dependency_links.txt
kkbtdht.egg-info/not-zip-safe
kkbtdht.egg-info/requires.txt
kkbtdht.egg-info/top_level.txt